{
  "consents": [
    {
      "consentEmailTemplateId": "f0e9d738-c98d-45ee-b869-8636342c5158",
      "countryMinimumAgeForSelfConsent": {
        "de": 21
      },
      "data": {},
      "defaultMinimumAgeForSelfConsent": 18,
      "emailPlus": {
        "emailTemplateId": "f0e9d738-c98d-45ee-b869-8636342c5158",
        "enabled": true,
        "maximumTimeToSendEmailInHours": 48,
        "minimumTimeToSendEmailInHours": 24
      },
      "id": "e33aeba3-0a6d-4f0d-acfe-9225e548d838",
      "insertInstant": 1675362181409,
      "lastUpdateInstant": 1675362181409,
      "multipleValuesAllowed": false,
      "name": "Patient Consent",
      "values": [
        "Written",
        "Verbal"
      ]
    }
  ],
  "total": 1
}
